lockatme/__init__.py
lockatme/__main__.py
lockatme/__version__.py
lockatme/auth.py
lockatme/cli.py
lockatme/lock.py
lockatme/unlockers/__init__.py
lockatme/unlockers/facial_recognition.py
lockatme/unlockers/password.py
lockatme-0.0.3.dist-info/LICENSE
lockatme-0.0.3.dist-info/METADATA
lockatme-0.0.3.dist-info/WHEEL
lockatme-0.0.3.dist-info/entry_points.txt
lockatme-0.0.3.dist-info/top_level.txt
lockatme-0.0.3.dist-info/RECORD
