Metadata-Version: 2.1
Name: lockatme
Version: 0.0.3
Summary: Modulable screen locker
Home-page: https://github.com/Sweenu/lockatme
Author: Pierre-Louis Sergent, David Anandanadaradja, Matthieu Kirschleger, Sagar Gueye, Bruno Inec
Author-email: brunoinec@gmail.com
License: MIT
Platform: UNKNOWN
Classifier: Development Status :: 2 - Pre-Alpha
Classifier: License :: OSI Approved :: MIT License
Classifier: Intended Audience :: End Users/Desktop
Classifier: Topic :: Desktop Environment :: Screen Savers
Classifier: Programming Language :: Python
Classifier: Programming Language :: Python :: 3
Classifier: Programming Language :: Python :: 3.6
Classifier: Programming Language :: Python :: Implementation :: CPython
Classifier: Operating System :: POSIX :: Linux
Classifier: Environment :: X11 Applications
Requires-Python: >=3.5.0
Requires-Dist: python-xlib
Requires-Dist: opencv-python
Requires-Dist: dlib
Requires-Dist: face-recognition
Requires-Dist: pamela
